marsh/__init__.py
marsh/bash/__init__.py
marsh/bash/bash_factory.py
marsh/bash/bash_grammar.py
marsh/bash/bash_runner_decorators.py
marsh/bash/bash_script.py
marsh/constants.py
marsh/core/__init__.py
marsh/core/authenticator.py
marsh/core/cmd_run_decorator.py
marsh/core/command_grammar.py
marsh/core/connector.py
marsh/core/conveyor.py
marsh/core/executor.py
marsh/core/expression.py
marsh/core/script.py
marsh/dag/__init__.py
marsh/dag/dag.py
marsh/dag/node.py
marsh/dag/startable.py
marsh/docker/__init__.py
marsh/docker/docker_command_grammar.py
marsh/docker/docker_executor.py
marsh/exceptions.py
marsh/logger.py
marsh/modifier_functions/__init__.py
marsh/modifier_functions/case_conversion.py
marsh/modifier_functions/readers.py
marsh/powershell/__init__.py
marsh/processor_functions/__init__.py
marsh/processor_functions/printers.py
marsh/processor_functions/raisers.py
marsh/processor_functions/redirections.py
marsh/signals.py
marsh/ssh/__init__.py
marsh/ssh/ssh_command_grammar.py
marsh/ssh/ssh_connector.py
marsh/ssh/ssh_factory.py
marsh/utils/__init__.py
marsh/utils/output_streams.py
marsh_lib-0.2.0.dist-info/LICENSE
marsh_lib-0.2.0.dist-info/METADATA
marsh_lib-0.2.0.dist-info/WHEEL
marsh_lib-0.2.0.dist-info/RECORD
