Metadata-Version: 2.3
Name: marsh-lib
Version: 0.2.0
Summary: Lightweight, extensible Python library for building, managing, and executing command workflows.
License: MIT
Keywords: marsh,marsh-lib
Author: Cedric Anover
Author-email: cedric.anover@hotmail.com
Requires-Python: >=3.10,<3.13
Classifier: Development Status :: 3 - Alpha
Classifier: License :: OSI Approved :: MIT License
Classifier: Operating System :: Microsoft :: Windows
Classifier: Operating System :: POSIX :: Linux
Classifier: Programming Language :: Python :: 3
Classifier: Programming Language :: Python :: 3.10
Classifier: Programming Language :: Python :: 3.11
Classifier: Programming Language :: Python :: 3.12
Classifier: Topic :: Software Development :: Libraries
Classifier: Topic :: Software Development :: Libraries :: Python Modules
Classifier: Topic :: System :: Shells
Classifier: Topic :: System :: System Shells
Classifier: Topic :: System :: Systems Administration
Classifier: Topic :: Utilities
Requires-Dist: docker (>=7.1.0,<8.0.0)
Requires-Dist: fabric (>=3.2.2,<4.0.0)
Project-URL: Repository, https://github.com/CedricAnover/marsh
